example_package/__init__.py
example_package/read_file.py
Read_File_Devika_P-0.2.dist-info/METADATA
Read_File_Devika_P-0.2.dist-info/WHEEL
Read_File_Devika_P-0.2.dist-info/licence.txt
Read_File_Devika_P-0.2.dist-info/top_level.txt
Read_File_Devika_P-0.2.dist-info/RECORD
