Metadata-Version: 2.1
Name: Read-File-Devika-P
Version: 0.2
Summary: A Python package to read data from .yaml and .cfg or config files. It creates .json and .env fileto the input file and writes data. Also loads environment variables as per configuration file. 
Home-page: https://github.com/Zekardo/MyProjects.git
Author: Devika Paranjpe
Author-email: dpmp1986@gmail.com
